Metadata-Version: 1.0
Name: function-validator
Version: 0.1
Summary: UNKNOWN
Home-page: https://github.com/anandtripathi5/function_validator
Author: Anand Tripathi
Author-email: anand.tripathi507@gmail.com
License: UNKNOWN
Platform: UNKNOWN
